LICENSE
MANIFEST.in
README.rst
setup.py
django_periodically.egg-info/PKG-INFO
django_periodically.egg-info/SOURCES.txt
django_periodically.egg-info/dependency_links.txt
django_periodically.egg-info/top_level.txt
exampleapp/__init__.py
exampleapp/models.py
exampleapp/periodictasks.py
exampleapp/tests.py
exampleapp/views.py
periodically/__init__.py
periodically/backends.py
periodically/decorators.py
periodically/models.py
periodically/schedules.py
periodically/settings.py
periodically/signals.py
periodically/tasks.py
periodically/tests.py
periodically/utils.py
periodically/views.py
periodically/management/__init__.py
periodically/management/commands/__init__.py
periodically/management/commands/runtasks.py
periodically/migrations/0001_initial.py
periodically/migrations/0002_charfield_schedule_id.py
periodically/migrations/__init__.py