Metadata-Version: 1.0
Name: django-periodically
Version: 0.3.0
Summary: Periodic task management for your Django projects.
Home-page: https://github.com/hzdg/django-periodically
Author: Matthew Tretter
Author-email: matthew@exanimo.com
License: UNKNOWN
Platform: UNKNOWN
